README.txt
setup.py
collective/__init__.py
collective.portlet.userActionsPortlet.egg-info/PKG-INFO
collective.portlet.userActionsPortlet.egg-info/SOURCES.txt
collective.portlet.userActionsPortlet.egg-info/dependency_links.txt
collective.portlet.userActionsPortlet.egg-info/entry_points.txt
collective.portlet.userActionsPortlet.egg-info/namespace_packages.txt
collective.portlet.userActionsPortlet.egg-info/not-zip-safe
collective.portlet.userActionsPortlet.egg-info/requires.txt
collective.portlet.userActionsPortlet.egg-info/top_level.txt
collective/portlet/__init__.py
collective/portlet/userActionsPortlet/__init__.py
collective/portlet/userActionsPortlet/configure.zcml
collective/portlet/userActionsPortlet/useractionsportlet.pt
collective/portlet/userActionsPortlet/useractionsportlet.py
collective/portlet/userActionsPortlet/version.txt
collective/portlet/userActionsPortlet/profiles/default/metadata.xml
collective/portlet/userActionsPortlet/profiles/default/portlets.xml
collective/portlet/userActionsPortlet/tests/__init__.py
collective/portlet/userActionsPortlet/tests/base.py
collective/portlet/userActionsPortlet/tests/test_portlet.py
docs/HISTORY.txt
docs/INSTALL.txt
docs/LICENSE.GPL
docs/LICENSE.txt