Metadata-Version: 1.0
Name: collective.portlet.userActionsPortlet
Version: 0.2
Summary: Portlet with the same function as the user actions viewlet
Home-page: http://svn.plone.org/svn/collective/
Author: David Jonas
Author-email: davidjonasdesign@gmail.com
License: GPL
Keywords: plone portlet user actions login
Platform: UNKNOWN
Classifier: Framework :: Plone
Classifier: Programming Language :: Python
